LICENSE
MANIFEST.in
README.rst
VERSION
requirements.txt
setup.py
atomshieldscli/__init__.py
atomshieldscli/banner.py
atomshieldscli/cli.py
atomshieldscli.egg-info/PKG-INFO
atomshieldscli.egg-info/SOURCES.txt
atomshieldscli.egg-info/dependency_links.txt
atomshieldscli.egg-info/requires.txt
atomshieldscli.egg-info/top_level.txt