Metadata-Version: 1.1
Name: atomshieldscli
Version: 1.9
Summary: Command-Line Interface for atomshields package.
Home-page: https://github.com/ElevenPaths/AtomShields-cli
Author: ElevenPaths
Author-email: diego.fernandez@11paths.com, david.amrani@11paths.com
License: Apache 2.0
Download-URL: https://github.com/ElevenPaths/AtomShields-cli/tarball/1.9
Keywords: security,source code,analysis
Platform: UNKNOWN
Classifier: Development Status :: 4 - Beta
Classifier: Intended Audience :: Developers
Classifier: Intended Audience :: Other Audience
Classifier: License :: OSI Approved :: Apache Software License
Classifier: Natural Language :: English
Classifier: Operating System :: OS Independent
Classifier: Programming Language :: Python :: 2.7
Classifier: Topic :: Software Development :: Libraries :: Python Modules
Classifier: Topic :: Software Development :: Quality Assurance
Classifier: Topic :: Software Development :: Testing
